LICENSE
README.md
setup.py
drone_yolo_client.egg-info/PKG-INFO
drone_yolo_client.egg-info/SOURCES.txt
drone_yolo_client.egg-info/dependency_links.txt
drone_yolo_client.egg-info/entry_points.txt
drone_yolo_client.egg-info/requires.txt
drone_yolo_client.egg-info/top_level.txt
object_position_calculator/CoordinateCalculator.py
object_position_calculator/__init__.py
object_position_calculator/calculate.py
object_position_calculator/detect_object.py
object_position_calculator/newCalculator.py
object_position_calculator/object_position.py
object_position_calculator/position_calculator.py