Metadata-Version: 2.1
Name: drone-yolo-client
Version: 0.1.0
Summary: Drone YOLO client for object detection and server communication.
Author: Your Name
Author-email: your.email@example.com
License-File: LICENSE
